release_pypi/__init__.py
release_pypi/exceptions.py
release_pypi/topypi.py
release_pypi-3.0.0rc0.dist-info/LICENSE
release_pypi-3.0.0rc0.dist-info/METADATA
release_pypi-3.0.0rc0.dist-info/WHEEL
release_pypi-3.0.0rc0.dist-info/entry_points.txt
release_pypi-3.0.0rc0.dist-info/top_level.txt
release_pypi-3.0.0rc0.dist-info/RECORD
