Metadata-Version: 2.1
Name: release-pypi
Version: 3.0.0rc0
Summary: Simple PyPI uploader, using Twine.
Home-page: https://github.com/dfarre/release-pypi
Author-email: Daniel Farré Manzorro <d.farre.m@gmail.com>
Maintainer-email: Daniel Farré Manzorro <d.farre.m@gmail.com>
License: This piece of software is issued under the MIT License:
Project-URL: Homepage, https://github.com/dfarre/release-pypi
Project-URL: Bug Reports, https://github.com/dfarre/release-pypi/issues
Project-URL: Source, https://github.com/dfarre/release-pypi
Classifier: Programming Language :: Python :: 3
Classifier: Programming Language :: Python :: 3.11
Classifier: License :: OSI Approved :: MIT License
Classifier: Operating System :: OS Independent
Classifier: Intended Audience :: Developers
Classifier: Development Status :: 4 - Beta
Requires-Python: >=3.11
License-File: LICENSE
Requires-Dist: build
Requires-Dist: twine
Requires-Dist: packaging
Requires-Dist: simple-cmd
Requires-Dist: urllib3 <2.0
Provides-Extra: dev
Requires-Dist: ipdb ; extra == 'dev'
Requires-Dist: ipython ; extra == 'dev'
Provides-Extra: test
Requires-Dist: pytest-cov ; extra == 'test'
